recaptchav3py/__init__.py
recaptchav3py/constants.py
recaptchav3py/main.py
recaptchav3py-0.0.2.dist-info/LICENSE
recaptchav3py-0.0.2.dist-info/METADATA
recaptchav3py-0.0.2.dist-info/WHEEL
recaptchav3py-0.0.2.dist-info/top_level.txt
recaptchav3py-0.0.2.dist-info/RECORD
