Metadata-Version: 2.1
Name: recaptchav3py
Version: 0.0.2
Summary: UNKNOWN
Home-page: https://github.com/thicccat688/recaptchav3py
Author: Tomás Perestrelo
Author-email: tomasperestrelo21@gmail.com
License: MIT
Download-URL: https://pypi.org/project/recaptchav3py/
Keywords: python,google,recaptchav3
Platform: UNKNOWN
License-File: LICENSE
Requires-Dist: requests
